{
  "keywords": [
    {
      "NAMES": [
        "爪牙"
      ],
      "DESCRIPTION": "爪牙会在他们的领导者死亡时放弃战斗。"
    },
    {
      "NAMES": [
        "缠绕"
      ],
      "DESCRIPTION": "回合开始时失去生命。"
    },
    {
      "NAMES": [
        "缓冲"
      ],
      "DESCRIPTION": "阻挡1次伤害。"
    },
    {
      "NAMES": [
        "金属化"
      ],
      "DESCRIPTION": "回合结束时生成格挡。"
    },
    {
      "NAMES": [
        "多层护甲"
      ],
      "DESCRIPTION": "回合结束时生成格挡，收到未被格挡的伤害时减少层数。"
    },
    {
      "NAMES": [
        "柔韧"
      ],
      "DESCRIPTION": "受到未被格挡的伤害时，获得格挡。"
    },
    {
      "NAMES": [
        "再生"
      ],
      "DESCRIPTION": "回合结束时恢复生命。"
    },
    {
      "NAMES": [
        "真实伤害"
      ],
      "DESCRIPTION": "无视一切防御手段的伤害。"
    },

    {
      "NAMES": [
        "魔力充能"
      ],
      "DESCRIPTION": "使用 #y库洛牌 或 #y小樱牌 后产生的魔力残留，累积到一定数量后可以触发卡牌的特殊效果。"
    },
    {
      "NAMES": [
        "库洛牌"
      ],
      "DESCRIPTION": "能从各种途径被搜集到的牌。"
    },
    {
      "NAMES": [
        "小樱牌"
      ],
      "DESCRIPTION": "通过 #y转牌 ，从 #y库洛牌 转变而来的特殊牌。 NL  #y唯一 ，卡组中只会存在1张同名小樱牌，复制时只会得到同名的 #y库洛牌 。 NL 无法升级，且不触发 #y魔力充能 的效果。 NL 打出时，将添加1张 #y虚空 到弃牌堆。"
    },
    {
      "NAMES": [
        "转牌"
      ],
      "DESCRIPTION": "将 #y库洛牌 转变为 #y小樱牌 的 #y符咒 。 "
    },
    {
      "NAMES": [
        "符咒"
      ],
      "DESCRIPTION": "从事件中获得的特殊卡牌。"
    },
    {
      "NAMES": [
        "光元素牌"
      ],
      "DESCRIPTION": "光属性库洛牌，是 #y地属性 和 #y火属性 的上位属性，可以同时触发地、火两属性的效果。"
    },
    {
      "NAMES": [
        "暗元素牌"
      ],
      "DESCRIPTION": "暗属性库洛牌，是 #y水属性 和 #y风属性 的上位属性，可以同时触发水、风两属性的效果。"
    },
    {
      "NAMES": [
        "地"
      ],
      "DESCRIPTION": "即地元素牌，地属性库洛牌。连协成功时可以获得格挡。"
    },
    {
      "NAMES": [
        "地元素牌"
      ],
      "DESCRIPTION": "地属性库洛牌。连协成功时可以获得格挡。"
    },
    {
      "NAMES": [
        "水"
      ],
      "DESCRIPTION": "即水元素牌，水属性库洛牌。连协成功时可以获得能量。"
    },
    {
      "NAMES": [
        "水元素牌"
      ],
      "DESCRIPTION": "水属性库洛牌。连协成功时可以获得能量。"
    },
    {
      "NAMES": [
        "火"
      ],
      "DESCRIPTION": "即火元素牌，火属性库洛牌。连协成功时可以造成伤害。"
    },
    {
      "NAMES": [
        "火元素牌"
      ],
      "DESCRIPTION": "火属性库洛牌。连协成功时可以造成伤害。"
    },
    {
      "NAMES": [
        "风"
      ],
      "DESCRIPTION": "即风元素牌，风属性库洛牌。连协成功时可以抽牌。"
    },
    {
      "NAMES": [
        "风元素牌"
      ],
      "DESCRIPTION": "风属性库洛牌。连协成功时可以抽牌。"
    },
    {
      "NAMES": [
        "封印解除"
      ],
      "DESCRIPTION": "被 #y封印解除 的卡牌将变为 #b0 费，所有效果都将提高 #b25% ，并添加 #y虚无 和 #y消耗 属性。 NL 获得遗物 #y剑玉 后加成效果提高至 #b50% 。 NL 提升效果向下取整。"
    },
    {
      "NAMES": [
        "转化"
      ],
      "DESCRIPTION": "将 #y库洛牌 转化为 #y小樱牌 。只有卡组中不存在 对应 #y小樱牌 时，才能转化。转化成功后，对应 #y库洛牌 从卡组中移除，对应 #y小樱牌 加入卡组。"
    },
    {
      "NAMES": [
        "剑牌"
      ],
      "DESCRIPTION": "基础打击牌。"
    },
    {
      "NAMES": [
        "镜牌"
      ],
      "DESCRIPTION": "可以复制手牌的牌。"
    },
    {
      "NAMES": [
        "声牌"
      ],
      "DESCRIPTION": "无法被打出的库洛牌，抽到该牌时额外抽1张牌，被消耗时才会触发卡牌效果。"
    },
    {
      "NAMES": [
        "雨牌"
      ],
      "DESCRIPTION": "减少其余手牌耗能的牌。"
    },
    {
      "NAMES": [
        "雪牌"
      ],
      "DESCRIPTION": "可以根据 #y魔力充能 数量逐渐强化的牌。"
    },
    {
      "NAMES": [
        "岚牌"
      ],
      "DESCRIPTION": "对单体目标造成多次伤害的攻击牌。"
    },
    {
      "NAMES": [
        "雷牌"
      ],
      "DESCRIPTION": "可以造成巨量伤害的稀有攻击牌。"
    },
    {
      "NAMES": [
        "雾牌"
      ],
      "DESCRIPTION": "可以瓦解敌人防御手段的牌。"
    },
    {
      "NAMES": [
        "封印之杖"
      ],
      "DESCRIPTION": "击杀敌人可以获得充能，当充能满足条件时，可以将 #y库洛牌 转变为 #y小樱牌 。"
    },
    {
      "NAMES": [
        "空道符"
      ],
      "DESCRIPTION": "可以改变属性的消耗性攻击卡。"
    },
    {
      "NAMES": [
        "火神"
      ],
      "DESCRIPTION": "对单体目标造成伤害的 #y火 属性的消耗型攻击卡。"
    },
    {
      "NAMES": [
        "雷帝"
      ],
      "DESCRIPTION": "对随机单体目标造成伤害的 #y地 属性的消耗型攻击卡。"
    },
    {
      "NAMES": [
        "风华"
      ],
      "DESCRIPTION": "对单体目标造成多次伤害的 #y风 属性的消耗型攻击卡。"
    },
    {
      "NAMES": [
        "水龙"
      ],
      "DESCRIPTION": "对全体敌人造成伤害的 #y水 属性的消耗型攻击卡。"
    },
    {
      "NAMES": [
        "沉睡"
      ],
      "DESCRIPTION": "目标陷入无法行动状态，受到伤害时醒来。 #y自然醒来 时恢复所有生命，并获得 #b2 层 #y虚弱 。"
    }
  ]
}